{
  "id": "poll-should-i-change-the-way-i-use-ai-generated-images",
  "title": "Poll: Should I change the way I use AI-generated images?",
  "status": "published",
  "authors": [
    "alex"
  ],
  "titleImage": "elliott-stallion-1UY8UuUkids-unsplash-scaled.jpg",
  "excerpt": "A couple of weeks ago, I wrote a post about one of my coworkers who enjoys dressing as a femboy. In the comments, I received quite a bit of feedback about the AI-generated image I used.\n",
  "categories": [
    "polls"
  ],
  "tags": [],
  "publishedDate": "2024-07-23T16:57:00",
  "updatedAt": "2024-07-16T12:21:54",
  "wordpressId": 4313
}