{
  "id": "lets-normalize-boys-wearing-dresses",
  "title": "Let’s Normalize Boys Wearing Dresses",
  "status": "published",
  "authors": [
    "alex"
  ],
  "excerpt": "This wonderful article is an interesting take from a mom&#8217;s perspective on her young son wanting to wear dresses.\n",
  "categories": [
    "gender",
    "in-the-media",
    "skirts-and-dresses"
  ],
  "tags": [
    "boys",
    "fashion",
    "genderless"
  ],
  "publishedDate": "2024-02-09T16:09:00",
  "updatedAt": "2023-11-16T17:14:34",
  "wordpressId": 2094
}