{
  "id": "the-beskirted-lumberjack-an-outfit",
  "title": "The Beskirted Lumberjack – An Outfit",
  "status": "published",
  "authors": [
    "alex"
  ],
  "titleImage": "IMG_4027-scaled.jpeg",
  "excerpt": "It&#8217;s been a while since my last outfit post and this one features one of my all-time favorite outfits which I have lovingly dubbed &#8220;The Beskirted Lumberjack&#8221;.\n",
  "categories": [
    "high-heels",
    "outfits",
    "skirts-and-dresses",
    "styling"
  ],
  "tags": [
    "fashion",
    "men in heels",
    "men in skirts"
  ],
  "publishedDate": "2024-11-06T09:03:00",
  "updatedAt": "2024-10-31T22:05:20",
  "wordpressId": 5041
}